translator.py
viki3lang-1.2.0.dist-info/METADATA
viki3lang-1.2.0.dist-info/WHEEL
viki3lang-1.2.0.dist-info/entry_points.txt
viki3lang-1.2.0.dist-info/top_level.txt
viki3lang-1.2.0.dist-info/RECORD
